lintro/__init__.py
lintro/__main__.py
lintro/_tool_versions.py
lintro/cli.py
lintro/ascii-art/fail.txt
lintro/ascii-art/success.txt
lintro/cli_utils/__init__.py
lintro/cli_utils/command_chainer.py
lintro/cli_utils/commands/__init__.py
lintro/cli_utils/commands/check.py
lintro/cli_utils/commands/config.py
lintro/cli_utils/commands/doctor.py
lintro/cli_utils/commands/format.py
lintro/cli_utils/commands/init.py
lintro/cli_utils/commands/list_tools.py
lintro/cli_utils/commands/test.py
lintro/cli_utils/commands/versions.py
lintro/config/__init__.py
lintro/config/config_loader.py
lintro/config/enforce_config.py
lintro/config/execution_config.py
lintro/config/lintro_config.py
lintro/config/tool_config.py
lintro/config/tool_config_generator.py
lintro/enums/__init__.py
lintro/enums/action.py
lintro/enums/bandit_levels.py
lintro/enums/boolean_string.py
lintro/enums/config_format.py
lintro/enums/config_key.py
lintro/enums/display_column.py
lintro/enums/env_bool.py
lintro/enums/git_command.py
lintro/enums/git_ref.py
lintro/enums/group_by.py
lintro/enums/hadolint_enums.py
lintro/enums/hyphenated_str_enum.py
lintro/enums/output_format.py
lintro/enums/pydoclint_style.py
lintro/enums/pytest_enums.py
lintro/enums/semgrep_enums.py
lintro/enums/severity_level.py
lintro/enums/tool_name.py
lintro/enums/tool_option_key.py
lintro/enums/tool_order.py
lintro/enums/tool_type.py
lintro/enums/tools_value.py
lintro/enums/uppercase_str_enum.py
lintro/enums/yamllint_format.py
lintro/exceptions/__init__.py
lintro/exceptions/errors.py
lintro/formatters/__init__.py
lintro/formatters/formatter.py
lintro/formatters/core/__init__.py
lintro/formatters/core/format_registry.py
lintro/formatters/styles/__init__.py
lintro/formatters/styles/csv.py
lintro/formatters/styles/grid.py
lintro/formatters/styles/html.py
lintro/formatters/styles/json.py
lintro/formatters/styles/markdown.py
lintro/formatters/styles/plain.py
lintro/models/__init__.py
lintro/models/core/__init__.py
lintro-0.42.6.dist-info/licenses/LICENSE
lintro-0.42.6.dist-info/METADATA
lintro-0.42.6.dist-info/WHEEL
lintro-0.42.6.dist-info/entry_points.txt
lintro-0.42.6.dist-info/top_level.txt
lintro-0.42.6.dist-info/RECORD
