Metadata-Version: 2.4
Name: lintro
Version: 0.42.6
Summary: A unified CLI tool for code formatting, linting, and quality assurance
Author-email: lgtm-hq <turbocoder13@gmail.com>
License: MIT License
Project-URL: Homepage, https://github.com/lgtm-hq/py-lintro
Project-URL: Documentation, https://github.com/lgtm-hq/py-lintro/docs
Project-URL: Source, https://github.com/lgtm-hq/py-lintro
Keywords: linting,formatting,code-quality,cli,python,javascript,yaml,docker
Classifier: Development Status :: 4 - Beta
Classifier: Intended Audience :: Developers
Classifier: Operating System :: OS Independent
Classifier: Programming Language :: Python :: 3
Classifier: Programming Language :: Python :: 3.11
Classifier: Programming Language :: Python :: 3.12
Classifier: Programming Language :: Python :: 3.13
Classifier: Topic :: Software Development :: Quality Assurance
Classifier: Topic :: Software Development :: Libraries :: Python Modules
Classifier: Topic :: Utilities
Requires-Python: >=3.11
License-File: LICENSE
Requires-Dist: click==8.1.8
Requires-Dist: coverage-badge==1.1.2
Requires-Dist: loguru==0.7.3
Requires-Dist: packaging>=25.0
Requires-Dist: pathspec>=0.12.1
Requires-Dist: pydantic>=2.12.5
Requires-Dist: rich>=14.2.0
Requires-Dist: tabulate==0.9.0
Requires-Dist: yamllint==1.37.1
Requires-Dist: httpx==0.28.1
Requires-Dist: defusedxml==0.7.1
Requires-Dist: ruff>=0.14.10
Requires-Dist: black>=25.12.0
Requires-Dist: bandit>=1.9.2
Requires-Dist: mypy>=1.19.1
Requires-Dist: pydoclint>=0.8.3
Provides-Extra: dev
Requires-Dist: pytest==9.0.2; extra == "dev"
Requires-Dist: pytest-cov==7.0.0; extra == "dev"
Requires-Dist: pytest-mock==3.15.1; extra == "dev"
Requires-Dist: pytest-xdist==3.8.0; extra == "dev"
Requires-Dist: pytest-sugar==1.1.1; extra == "dev"
Requires-Dist: tox==4.34.1; extra == "dev"
Requires-Dist: allure-pytest==2.15.3; extra == "dev"
Requires-Dist: ruff; extra == "dev"
Requires-Dist: mypy; extra == "dev"
Requires-Dist: coverage-badge==1.1.2; extra == "dev"
Requires-Dist: python-semantic-release==10.5.3; extra == "dev"
Requires-Dist: assertpy==1.1; extra == "dev"
Requires-Dist: httpx==0.28.1; extra == "dev"
Provides-Extra: test
Requires-Dist: pytest==9.0.2; extra == "test"
Requires-Dist: pytest-cov==7.0.0; extra == "test"
Requires-Dist: pytest-mock==3.15.1; extra == "test"
Requires-Dist: pytest-xdist==3.8.0; extra == "test"
Requires-Dist: assertpy==1.1; extra == "test"
Provides-Extra: typing
Requires-Dist: types-setuptools==80.9.0.20251223; extra == "typing"
Requires-Dist: types-tabulate==0.9.0.20241207; extra == "typing"
Provides-Extra: tools
Requires-Dist: semgrep>=1.85.0; extra == "tools"
Requires-Dist: sqlfluff>=4.0.0; extra == "tools"
Dynamic: license-file
